LICENSE
README.md
setup.py
eqlog/__init__.py
eqlog.egg-info/PKG-INFO
eqlog.egg-info/SOURCES.txt
eqlog.egg-info/dependency_links.txt
eqlog.egg-info/top_level.txt
eqlog/components/__init__.py
eqlog/components/create_log_file.py
eqlog/components/file_option.py
eqlog/main/__init__.py
eqlog/main/log.py